wiliot/__init__.py
wiliot/__init__extended__.py
wiliot/get_version.py
wiliot/requirements.txt
wiliot/version.py
wiliot/wiliot2.gif
wiliot/wiliot_cloud/__init__.py
wiliot/wiliot_cloud/api_client.py
wiliot/wiliot_cloud/edge/__init__.py
wiliot/wiliot_cloud/edge/edge.py
wiliot/wiliot_cloud/edge/examples/__init__.py
wiliot/wiliot_cloud/edge/examples/edge_api.py
wiliot/wiliot_cloud/management/__init__.py
wiliot/wiliot_cloud/management/management.py
wiliot/wiliot_cloud/management/examples/__init__.py
wiliot/wiliot_cloud/management/examples/management_api.py
wiliot/wiliot_cloud/manufacturing/__init__.py
wiliot/wiliot_cloud/manufacturing/manufacturing.py
wiliot/wiliot_cloud/manufacturing/examples/__init__.py
wiliot/wiliot_cloud/manufacturing/examples/mannufacturing_api.py
wiliot/wiliot_cloud/platform/__init__.py
wiliot/wiliot_cloud/platform/platform.py
wiliot/wiliot_cloud/platform/examples/__init__.py
wiliot/wiliot_cloud/platform/examples/platform_api.py
wiliot/wiliot_cloud/security/__init__.py
wiliot/wiliot_cloud/security/security.py
wiliot/wiliot_cloud/traceability/__init__.py
wiliot/wiliot_cloud/traceability/traceability.py
wiliot/wiliot_cloud/user/__init__.py
wiliot/wiliot_cloud/user/user.py
wiliot/wiliot_core/__init__.py
wiliot/wiliot_core/update_wiliot_packages.py
wiliot/wiliot_core/utils.py
wiliot/wiliot_core/local_gateway/__init__.py
wiliot/wiliot_core/local_gateway/continuous_listener.py
wiliot/wiliot_core/local_gateway/custom_energy_pattern.py
wiliot/wiliot_core/local_gateway/local_gateway_core.py
wiliot/wiliot_core/local_gateway/examples/__init__.py
wiliot/wiliot_core/local_gateway/examples/local_gateway_basic_example.py
wiliot/wiliot_core/packet_data/__init__.py
wiliot/wiliot_core/packet_data/packet.py
wiliot/wiliot_core/packet_data/packet_list.py
wiliot/wiliot_core/packet_data/tag_collection.py
wiliot/wiliot_deployment_tools/__init__.py
wiliot/wiliot_testers/API_README.md
wiliot/wiliot_testers/README.md
wiliot/wiliot_testers/__init__.py
wiliot-3.10.14.dist-info/LICENSE
wiliot-3.10.14.dist-info/METADATA
wiliot-3.10.14.dist-info/WHEEL
wiliot-3.10.14.dist-info/top_level.txt
wiliot-3.10.14.dist-info/RECORD
