Metadata-Version: 2.1
Name: wiliot
Version: 3.10.14
Summary: A library for interacting with Wiliot's private API
Home-page: UNKNOWN
Author: Wiliot
Author-email: support@wiliot.com
License: MIT
Project-URL: Bug Tracker, https://WILIOT-ZENDESK-URL
Platform: UNKNOWN
Classifier: Programming Language :: Python :: 3
Classifier: License :: OSI Approved :: MIT License
Classifier: Operating System :: OS Independent
Requires-Python: >=3.6
License-File: LICENSE
Requires-Dist: requests
Requires-Dist: setuptools-scm
Provides-Extra: advance
Requires-Dist: pyserial ; extra == 'advance'
Requires-Dist: pc-ble-driver-py ; extra == 'advance'
Requires-Dist: nrfutil ; extra == 'advance'
Requires-Dist: yoctopuce ; extra == 'advance'
Requires-Dist: pandas ; extra == 'advance'
Requires-Dist: numpy ; extra == 'advance'
Requires-Dist: pyqtgraph ; extra == 'advance'
Requires-Dist: PySimpleGUI ; extra == 'advance'
Requires-Dist: matplotlib ; extra == 'advance'
Requires-Dist: PyQt5 ; extra == 'advance'
Requires-Dist: pygubu (==0.16) ; extra == 'advance'
Requires-Dist: MarkupSafe (==2.0.1) ; extra == 'advance'
Requires-Dist: bokeh (==2.4.1) ; extra == 'advance'
Requires-Dist: importlib-metadata ; extra == 'advance'
Requires-Dist: pyjwt ; extra == 'advance'
Requires-Dist: pycryptodome (==3.14.1) ; extra == 'advance'
Requires-Dist: appdirs ; extra == 'advance'
Requires-Dist: tabulate ; extra == 'advance'
Requires-Dist: tqdm ; extra == 'advance'
Requires-Dist: pillow ; extra == 'advance'
Requires-Dist: dash ; extra == 'advance'
Requires-Dist: plotly ; extra == 'advance'
Provides-Extra: offline_env
Requires-Dist: winshell ; extra == 'offline_env'
Requires-Dist: pypiwin32 ; extra == 'offline_env'
Requires-Dist: appdirs ; extra == 'offline_env'
Requires-Dist: PySimpleGUI ; extra == 'offline_env'
